__init__.py
combine_settings.py
combine_settings-1.1.0.dist-info/LICENSE
combine_settings-1.1.0.dist-info/METADATA
combine_settings-1.1.0.dist-info/WHEEL
combine_settings-1.1.0.dist-info/top_level.txt
combine_settings-1.1.0.dist-info/RECORD
