Metadata-Version: 2.1
Name: combine-settings
Version: 1.1.0
Summary: Combine application settings from multiple files
Author-email: David Willcox <daw30410@yahoo.com>
License: Apache License
Project-URL: Homepage, https://github.com/dawillcox/python_combine_settings
Project-URL: Bug Tracker, https://github.com/dawillcox/python_combine_settings/issues
Project-URL: Documentation, https://github.com/dawillcox/python_combine_settings/blob/main/README.md
Project-URL: Repository, https://github.com//dawillcox/python_combine_settings.git
Project-URL: Changelog, https://github.com/dawillcox/python_combine_settings/blob/main/CHANGELOG.md
Classifier: Programming Language :: Python :: 3
Classifier: License :: OSI Approved :: MIT License
Classifier: Operating System :: OS Independent
Requires-Python: >=3.7
License-File: LICENSE
Requires-Dist: platformdirs >=2.5.2
Requires-Dist: PyYAML >=6.0
